replaceall/__init__.py
replaceall/replaceall.py
replaceall-1.0.dist-info/DESCRIPTION.rst
replaceall-1.0.dist-info/METADATA
replaceall-1.0.dist-info/RECORD
replaceall-1.0.dist-info/WHEEL
replaceall-1.0.dist-info/metadata.json
replaceall-1.0.dist-info/top_level.txt
