Metadata-Version: 2.0
Name: replaceall
Version: 1.0
Summary: Replaces or removes one or more Chars in a String!
Home-page: https://github.com/ypsman/py-replaceall.git
Author: Yves Sanderbrand
Author-email: yvessander@gmail.com
License: GPL
Platform: UNKNOWN
Classifier: License :: OSI Approved :: GNU General Public License v3 (GPLv3)
Classifier: Programming Language :: Python :: 2.7
Classifier: Programming Language :: Python :: 3
